plimverai_sdk-1.0.0.dist-info/licenses/LICENSE
zenuxai_sdk/__init__.py
zenuxai_sdk/zenuxai.py
plimverai_sdk-1.0.0.dist-info/METADATA
plimverai_sdk-1.0.0.dist-info/WHEEL
plimverai_sdk-1.0.0.dist-info/top_level.txt
plimverai_sdk-1.0.0.dist-info/RECORD
