Metadata-Version: 2.4
Name: plimverai-sdk
Version: 1.0.0
Summary: Official Python SDK for PlimverAI API - Chat, RAG, Memory, Grounding
Home-page: https://github.com/Elliot-Elikplim/Zenux-Api
Author: PlimverAI Team
Author-email: PlimverAI Team <support@plimverai.com>
License: MIT
Project-URL: Homepage, https://github.com/Elliot-Elikplim/Zenux-Api
Project-URL: Documentation, https://github.com/Elliot-Elikplim/Zenux-Api/tree/master/docs
Project-URL: Repository, https://github.com/Elliot-Elikplim/Zenux-Api
Project-URL: Issues, https://github.com/Elliot-Elikplim/Zenux-Api/issues
Keywords: plimverai,ai,llm,chat,rag,memory,grounding,openai
Classifier: Development Status :: 5 - Production/Stable
Classifier: Intended Audience :: Developers
Classifier: License :: OSI Approved :: MIT License
Classifier: Programming Language :: Python :: 3
Classifier: Programming Language :: Python :: 3.8
Classifier: Programming Language :: Python :: 3.9
Classifier: Programming Language :: Python :: 3.10
Classifier: Programming Language :: Python :: 3.11
Classifier: Programming Language :: Python :: 3.12
Classifier: Topic :: Software Development :: Libraries :: Python Modules
Classifier: Topic :: Scientific/Engineering :: Artificial Intelligence
Requires-Python: >=3.8
License-File: LICENSE
Requires-Dist: requests>=2.31.0
Requires-Dist: aiohttp>=3.9.0
Provides-Extra: dev
Requires-Dist: pytest>=7.4.0; extra == "dev"
Requires-Dist: pytest-asyncio>=0.21.0; extra == "dev"
Requires-Dist: pytest-cov>=4.1.0; extra == "dev"
Requires-Dist: black>=23.7.0; extra == "dev"
Requires-Dist: flake8>=6.1.0; extra == "dev"
Requires-Dist: mypy>=1.5.0; extra == "dev"
Dynamic: author
Dynamic: home-page
Dynamic: license-file
Dynamic: requires-python
